FrozenJson/__init__.py
FrozenJson/core.py
frozenjson-0.0.3.dist-info/METADATA
frozenjson-0.0.3.dist-info/WHEEL
frozenjson-0.0.3.dist-info/top_level.txt
frozenjson-0.0.3.dist-info/RECORD
