Metadata-Version: 2.4
Name: FrozenJson
Version: 0.0.3
Summary: 使用属性表示法浏览类似JSON的对象的只读外观。
Author-email: tongqing <toneching@163.com>
License: MIT
Project-URL: Homepage, https://github.com/TongTsing/fluent-Python
Requires-Python: >=3.7
